{"tabs":[{"id":"ac463aba-8465-4fe8-bd65-d1a02aea4649","pane":"main","path":"C:\\Users\\PaulF\\Documents\\GitHub\\adc2-crossVideo\\config.xml","type":"projectSettings","mode":"form"},{"id":"6edf28be-38dd-433a-80ba-7b5cf5c6fbfc","pane":"main","current":true,"path":"C:\\Users\\PaulF\\Documents\\GitHub\\adc2-crossVideo\\resources\\dynamic\\default.html","type":"file"},{"id":"99b7696d-30a5-478e-ae7f-93008ce2f7a5","pane":"main","path":"C:\\Users\\PaulF\\Documents\\GitHub\\adc2-crossVideo\\resources\\dynamic\\init.js","type":"file"},{"id":"fcc7007c-5bf3-4a60-9b99-579e477db386","pane":"main","path":"C:\\Users\\PaulF\\Documents\\GitHub\\adc2-crossVideo\\resources\\dynamic\\styles.css","type":"file"},{"id":"11257916-64ae-4e76-836c-e0cc1c6050a7","pane":"main","path":"C:\\Users\\PaulF\\Documents\\GitHub\\adc2-crossVideo\\resources\\static\\mejs-skins.css","type":"file"},{"id":"666d2a19-a3b1-4e8f-9b29-5ecba10e28ea","pane":"main","path":"C:\\Users\\PaulF\\Documents\\GitHub\\adc2-crossVideo\\resources\\static\\default.css","type":"file"},{"id":"2b56e34a-2dd0-42a7-bc30-f043ab617405","pane":"main","path":"F:\\Adc\\crossVideo\\readme.md","type":"file"},{"id":"0a2155e6-bde7-4b27-9382-410ba5026774","pane":"main","path":"F:\\Adc\\crossVideo\\changelog.md","type":"file"},{"id":"fb066c4e-85f8-4e60-9bde-337225ed2840","pane":"main","path":"F:\\Adc\\crossVideo\\config.xml","type":"projectSettings","mode":"form","adxVersion":"2.0.0","adxType":"adc"}]}